odoo/addons/survey_placeholder/README.rst
odoo/addons/survey_placeholder/__init__.py
odoo/addons/survey_placeholder/__manifest__.py
odoo/addons/survey_placeholder/i18n/it.po
odoo/addons/survey_placeholder/i18n/survey_placeholder.pot
odoo/addons/survey_placeholder/models/__init__.py
odoo/addons/survey_placeholder/models/survey_question.py
odoo/addons/survey_placeholder/readme/CONFIGURE.rst
odoo/addons/survey_placeholder/readme/CONTRIBUTORS.rst
odoo/addons/survey_placeholder/readme/DESCRIPTION.rst
odoo/addons/survey_placeholder/readme/ROADMAP.rst
odoo/addons/survey_placeholder/static/description/icon.png
odoo/addons/survey_placeholder/static/description/index.html
odoo/addons/survey_placeholder/views/survey_question_views.xml
odoo/addons/survey_placeholder/views/survey_templates.xml
odoo_addon_survey_placeholder-15.0.1.0.0.7.dist-info/METADATA
odoo_addon_survey_placeholder-15.0.1.0.0.7.dist-info/WHEEL
odoo_addon_survey_placeholder-15.0.1.0.0.7.dist-info/top_level.txt
odoo_addon_survey_placeholder-15.0.1.0.0.7.dist-info/RECORD
